uvpipx/UvPipxModels.py
uvpipx/UvPipxModelsUpgrader.py
uvpipx/__init__.py
uvpipx/__main__.py
uvpipx/cmd_launcher.py
uvpipx/config.py
uvpipx/internal_libs/Logger.py
uvpipx/internal_libs/__init__.py
uvpipx/internal_libs/args.py
uvpipx/internal_libs/http_utils.py
uvpipx/internal_libs/misc.py
uvpipx/internal_libs/stylist.py
uvpipx/internal_libs/text_formatter.py
uvpipx/platform/__init__.py
uvpipx/platform/win.py
uvpipx/req_spec.py
uvpipx/uvpipx_all.py
uvpipx/uvpipx_args.py
uvpipx/uvpipx_console_scripts.py
uvpipx/uvpipx_core.py
uvpipx/uvpipx_expose.py
uvpipx/uvpipx_infos.py
uvpipx/uvpipx_inject.py
uvpipx/uvpipx_install.py
uvpipx/uvpipx_run.py
uvpipx/uvpipx_upgrade.py
uvpipx/uvpipx_uv.py
uvpipx/uvpipx_venv_factory.py
uvpipx/uvpipx_venv_load.py
uvpipx/version.py
uvpipx-0.8.1.dist-info/LICENSE
uvpipx-0.8.1.dist-info/METADATA
uvpipx-0.8.1.dist-info/WHEEL
uvpipx-0.8.1.dist-info/entry_points.txt
uvpipx-0.8.1.dist-info/RECORD
