Metadata-Version: 2.3
Name: uvpipx
Version: 0.8.1
Summary: A small tool like pipx using uv behind the scene. Fast, Small ...
License: GPL
Author: Pytgaen
Author-email: 32298455+pytgaen@users.noreply.github.com
Requires-Python: >=3.8,<4.0
Classifier: License :: Other/Proprietary License
Classifier: Programming Language :: Python :: 3
Classifier: Programming Language :: Python :: 3.8
Classifier: Programming Language :: Python :: 3.9
Classifier: Programming Language :: Python :: 3.10
Classifier: Programming Language :: Python :: 3.11
Classifier: Programming Language :: Python :: 3.12
Classifier: Programming Language :: Python :: 3.13
Requires-Dist: uv (>=0.6.0,<1.0.0)
Project-URL: Homepage, https://uvpipx-pytgaen-group-cc4651f865d7ce5bdaea510cdc656d736634827532.gitlab.io
Project-URL: Repository, https://gitlab.com/pytgaen-group/uvpipx
